spacy_ann/__init__.py
spacy_ann/ann_kb.py
spacy_ann/ann_linker.py
spacy_ann/candidate_generator.py
spacy_ann/remote_ann_linker.py
spacy_ann/types.py
spacy_ann/api/__init__.py
spacy_ann/api/app.py
spacy_ann/api/constants.py
spacy_ann/api/example_request.json
spacy_ann/api/requirements.txt
spacy_ann/api/types.py
spacy_ann/cli/__init__.py
spacy_ann/cli/create_index.py
spacy_ann/cli/example_data.py
spacy_ann/cli/serve.py
spacy_ann_linker-0.3.3.dist-info/entry_points.txt
spacy_ann_linker-0.3.3.dist-info/LICENSE
spacy_ann_linker-0.3.3.dist-info/WHEEL
spacy_ann_linker-0.3.3.dist-info/METADATA
spacy_ann_linker-0.3.3.dist-info/RECORD
